argparsedirs/__init__.py
argparsedirs/argparsedirs.py
argparsedirs-0.2.1.dist-info/METADATA
argparsedirs-0.2.1.dist-info/WHEEL
argparsedirs-0.2.1.dist-info/RECORD
