Metadata-Version: 2.4
Name: argparsedirs
Version: 0.2.1
Summary: A simple extension for argparse to allow readable/writeable dir types
License: GPLv3
Author: Martin Baláž
Author-email: martin.balaz@trojsten.sk
Requires-Python: <4.0,>=3.10
Classifier: License :: Other/Proprietary License
Classifier: Programming Language :: Python :: 3
Classifier: Programming Language :: Python :: 3.10
Classifier: Programming Language :: Python :: 3.11
Classifier: Programming Language :: Python :: 3.12
Classifier: Programming Language :: Python :: 3.13
Classifier: Programming Language :: Python :: 3.14
Requires-Dist: argparse
Project-URL: Homepage, https://github.com/sesquideus/argparsedirs
